pyxblend/__init__.py
pyxblend-2.0.3.dist-info/licenses/LICENSE
pyxblend-2.0.3.dist-info/METADATA
pyxblend-2.0.3.dist-info/WHEEL
pyxblend-2.0.3.dist-info/top_level.txt
pyxblend-2.0.3.dist-info/RECORD
