Metadata-Version: 2.4
Name: pyxblend
Version: 2.0.3
Summary: Professional-grade Python obfuscation and Cython-based compilation suite.
Home-page: https://github.com/pythontoday/pyxblend
Author: PythonToday
Author-email: pythontodayz@gmail.com
Project-URL: Bug Reports, https://github.com/pythontoday/pyxblend/issues
Project-URL: Source, https://github.com/pythontoday/pyxblend
Project-URL: Documentation, https://github.com/pythontoday/pyxblend/wiki
Keywords: obfuscation,encryption,cython,security,protection,compilation
Classifier: Development Status :: 5 - Production/Stable
Classifier: Intended Audience :: Developers
Classifier: Intended Audience :: Information Technology
Classifier: License :: OSI Approved :: MIT License
Classifier: Programming Language :: Python :: 3
Classifier: Programming Language :: Python :: 3.8
Classifier: Programming Language :: Python :: 3.9
Classifier: Programming Language :: Python :: 3.10
Classifier: Programming Language :: Python :: 3.11
Classifier: Topic :: Security
Classifier: Topic :: Software Development :: Build Tools
Classifier: Topic :: Software Development :: Compilers
Requires-Python: >=3.8
License-File: LICENSE
Requires-Dist: python_minifier>=2.9.0
Requires-Dist: cython>=3.0.0
Dynamic: author
Dynamic: author-email
Dynamic: classifier
Dynamic: description
Dynamic: description-content-type
Dynamic: home-page
Dynamic: keywords
Dynamic: license-file
Dynamic: project-url
Dynamic: requires-dist
Dynamic: requires-python
Dynamic: summary
